tableau_mcp_navi/__init__.py
tableau_mcp_navi/__main__.py
tableau_mcp_navi/analytics.py
tableau_mcp_navi/client.py
tableau_mcp_navi/config.py
tableau_mcp_navi/models.py
tableau_mcp_navi/server.py
tableau_mcp_navi/tools/__init__.py
tableau_mcp_navi/tools/datasources.py
tableau_mcp_navi/tools/metadata.py
tableau_mcp_navi/tools/projects.py
tableau_mcp_navi/tools/users.py
tableau_mcp_navi/tools/views.py
tableau_mcp_navi/tools/workbooks.py
tableau_mcp_navi-0.1.0.dist-info/METADATA
tableau_mcp_navi-0.1.0.dist-info/WHEEL
tableau_mcp_navi-0.1.0.dist-info/entry_points.txt
tableau_mcp_navi-0.1.0.dist-info/licenses/LICENSE
tableau_mcp_navi-0.1.0.dist-info/RECORD
