Metadata-Version: 2.4
Name: tableau-mcp-navi
Version: 0.1.0
Summary: A Model Context Protocol (MCP) server for Tableau Server - enables AI assistants to interact with Tableau workbooks, views, datasources, and metadata
Project-URL: Homepage, https://github.com/manish-coder-1007/tableau-mcp-navi
Project-URL: Repository, https://github.com/manish-coder-1007/tableau-mcp-navi
Project-URL: Issues, https://github.com/manish-coder-1007/tableau-mcp-navi/issues
Author: Manish Balot
License-Expression: MIT
License-File: LICENSE
Keywords: ai,business-intelligence,data-visualization,llm,mcp,model-context-protocol,tableau
Classifier: Development Status :: 4 - Beta
Classifier: Intended Audience :: Developers
Classifier: License :: OSI Approved :: MIT License
Classifier: Programming Language :: Python :: 3
Classifier: Programming Language :: Python :: 3.10
Classifier: Programming Language :: Python :: 3.11
Classifier: Programming Language :: Python :: 3.12
Classifier: Topic :: Software Development :: Libraries :: Python Modules
Requires-Python: >=3.10
Requires-Dist: httpx>=0.27.0
Requires-Dist: mcp>=1.0.0
Requires-Dist: posthog>=3.0.0
Requires-Dist: pydantic>=2.0.0
Requires-Dist: python-dotenv>=1.0.0
Requires-Dist: requests>=2.31.0
Requires-Dist: tableauserverclient>=0.30
